README.md
setup.py
django_rest_framework_naming_style/__init__.py
django_rest_framework_naming_style/monkey.py
django_rest_framework_naming_style/naming.py
django_rest_framework_naming_style/parser.py
django_rest_framework_naming_style/renderer.py
django_rest_framework_naming_style/utils.py
django_rest_framework_naming_style.egg-info/PKG-INFO
django_rest_framework_naming_style.egg-info/SOURCES.txt
django_rest_framework_naming_style.egg-info/dependency_links.txt
django_rest_framework_naming_style.egg-info/not-zip-safe
django_rest_framework_naming_style.egg-info/top_level.txt