Metadata-Version: 1.2
Name: django-rest-framework-naming-style
Version: 0.2
Summary: A toolkit for Django REST framework to easily switch APIs' naming styles.
Home-page: https://github.com/zhanp/django-rest-framework-naming-style
Author: Fitz ZP
Author-email: zhanp.cn@gmail.com
License: MIT
Platform: UNKNOWN
Classifier: Development Status :: 4 - Beta
Classifier: License :: OSI Approved :: MIT License
Classifier: Programming Language :: Python :: 3
Classifier: Programming Language :: Python :: 3.5
Classifier: Framework :: Django :: 2.0
Classifier: Natural Language :: English
Classifier: Intended Audience :: Developers
Classifier: Topic :: Internet :: WWW/HTTP
Requires-Python: >=2.7
